{"name":"Check for Long Press and Alert","id":"search-using-appium-inspector;check-for-long-press-and-alert","testSteps":[{"number":1,"description":"Given Launch the application","duration":18102,"startTime":"2022-11-30T13:22:00.654+05:30[Asia/Calcutta]","result":"SUCCESS","precondition":false,"level":0},{"number":2,"description":"Then Check for long press","duration":9079,"startTime":"2022-11-30T13:22:18.760+05:30[Asia/Calcutta]","result":"SUCCESS","precondition":false,"level":0},{"number":3,"description":"Then Check for alert message","duration":50,"startTime":"2022-11-30T13:22:27.840+05:30[Asia/Calcutta]","exception":{"errorType":"org.openqa.selenium.NoSuchElementException","message":"An element could not be located on the page using the given search parameters.\nFor documentation on this error, please visit: https://selenium.dev/exceptions/#no_such_element\nBuild info: version: \u00274.5.0\u0027, revision: \u0027fe167b119a\u0027\nSystem info: os.name: \u0027Windows 10\u0027, os.arch: \u0027amd64\u0027, os.version: \u002710.0\u0027, java.version: \u00271.8.0_352\u0027\nDriver info: io.appium.java_client.android.AndroidDriver\nCommand: [a2840bad-ebd8-4ce5-8a16-353921c4160b, findElement {using\u003daccessibility id, value\u003dApp}]\nCapabilities {appium:app: C:\\Users\\kr.pandey\\Download..., appium:appPackage: io.appium.android.apis, appium:databaseEnabled: false, appium:desired: {app: C:\\Users\\kr.pandey\\Download..., deviceName: Pixel 6 API 30, platformName: android, udid: emulator-5554}, appium:deviceApiLevel: 30, appium:deviceManufacturer: unknown, appium:deviceModel: Android SDK built for x86, appium:deviceName: emulator-5554, appium:deviceScreenDensity: 420, appium:deviceScreenSize: 1080x2400, appium:deviceUDID: emulator-5554, appium:javascriptEnabled: true, appium:locationContextEnabled: false, appium:networkConnectionEnabled: true, appium:pixelRatio: 2.625, appium:platformVersion: 11, appium:statBarHeight: 136, appium:takesScreenshot: true, appium:udid: emulator-5554, appium:viewportRect: {height: 2002, left: 0, top: 136, width: 1080}, appium:warnings: {}, appium:webStorageEnabled: false, platformName: ANDROID}\nSession ID: a2840bad-ebd8-4ce5-8a16-353921c4160b\nFor documentation on this error, please visit: https://selenium.dev/exceptions/#no_such_element\nBuild info: version: \u00274.5.0\u0027, revision: \u0027fe167b119a\u0027\nSystem info: os.name: \u0027Windows 10\u0027, os.arch: \u0027amd64\u0027, os.version: \u002710.0\u0027, java.version: \u00271.8.0_352\u0027\nDriver info: driver.version: unknown","stackTrace":[{"declaringClass":"io.appium.java_client.remote.AppiumCommandExecutor","methodName":"execute","fileName":"AppiumCommandExecutor.java","lineNumber":189},{"declaringClass":"stepDefinitions.Demo","methodName":"checkAlertMessage","fileName":"Demo.java","lineNumber":60},{"declaringClass":"✽","methodName":"Check for alert message","fileName":"file:///C:/Users/kr.pandey/IdeaProjects/mobileAutomationProject/src/test/resources/features/feature.feature","lineNumber":16}]},"result":"ERROR","precondition":false,"level":0}],"userStory":{"id":"search-using-appium-inspector","storyName":"Search using Appium Inspector","displayName":"Search using Appium Inspector","path":"feature.feature","type":"feature"},"featureTag":{"name":"Search using Appium Inspector","type":"feature","displayName":"Search using Appium Inspector"},"title":"Check for Long Press and Alert","description":"","tags":[{"name":"Search using Appium Inspector","type":"feature","displayName":"Search using Appium Inspector"},{"name":"Task2","type":"tag","displayName":"Task2"}],"startTime":"2022-11-30T13:22:00.553+05:30[Asia/Calcutta]","duration":27426,"testFailureCause":{"errorType":"org.openqa.selenium.NoSuchElementException","message":"An element could not be located on the page using the given search parameters.\nFor documentation on this error, please visit: https://selenium.dev/exceptions/#no_such_element\nBuild info: version: \u00274.5.0\u0027, revision: \u0027fe167b119a\u0027\nSystem info: os.name: \u0027Windows 10\u0027, os.arch: \u0027amd64\u0027, os.version: \u002710.0\u0027, java.version: \u00271.8.0_352\u0027\nDriver info: io.appium.java_client.android.AndroidDriver\nCommand: [a2840bad-ebd8-4ce5-8a16-353921c4160b, findElement {using\u003daccessibility id, value\u003dApp}]\nCapabilities {appium:app: C:\\Users\\kr.pandey\\Download..., appium:appPackage: io.appium.android.apis, appium:databaseEnabled: false, appium:desired: {app: C:\\Users\\kr.pandey\\Download..., deviceName: Pixel 6 API 30, platformName: android, udid: emulator-5554}, appium:deviceApiLevel: 30, appium:deviceManufacturer: unknown, appium:deviceModel: Android SDK built for x86, appium:deviceName: emulator-5554, appium:deviceScreenDensity: 420, appium:deviceScreenSize: 1080x2400, appium:deviceUDID: emulator-5554, appium:javascriptEnabled: true, appium:locationContextEnabled: false, appium:networkConnectionEnabled: true, appium:pixelRatio: 2.625, appium:platformVersion: 11, appium:statBarHeight: 136, appium:takesScreenshot: true, appium:udid: emulator-5554, appium:viewportRect: {height: 2002, left: 0, top: 136, width: 1080}, appium:warnings: {}, appium:webStorageEnabled: false, platformName: ANDROID}\nSession ID: a2840bad-ebd8-4ce5-8a16-353921c4160b\nFor documentation on this error, please visit: https://selenium.dev/exceptions/#no_such_element\nBuild info: version: \u00274.5.0\u0027, revision: \u0027fe167b119a\u0027\nSystem info: os.name: \u0027Windows 10\u0027, os.arch: \u0027amd64\u0027, os.version: \u002710.0\u0027, java.version: \u00271.8.0_352\u0027\nDriver info: driver.version: unknown","stackTrace":[{"declaringClass":"io.appium.java_client.remote.AppiumCommandExecutor","methodName":"execute","fileName":"AppiumCommandExecutor.java","lineNumber":189},{"declaringClass":"stepDefinitions.Demo","methodName":"checkAlertMessage","fileName":"Demo.java","lineNumber":60},{"declaringClass":"✽","methodName":"Check for alert message","fileName":"file:///C:/Users/kr.pandey/IdeaProjects/mobileAutomationProject/src/test/resources/features/feature.feature","lineNumber":16}]},"testFailureClassname":"org.openqa.selenium.NoSuchElementException","testFailureMessage":"An element could not be located on the page using the given search parameters.\nFor documentation on this error, please visit: https://selenium.dev/exceptions/#no_such_element\nBuild info: version: \u00274.5.0\u0027, revision: \u0027fe167b119a\u0027\nSystem info: os.name: \u0027Windows 10\u0027, os.arch: \u0027amd64\u0027, os.version: \u002710.0\u0027, java.version: \u00271.8.0_352\u0027\nDriver info: io.appium.java_client.android.AndroidDriver\nCommand: [a2840bad-ebd8-4ce5-8a16-353921c4160b, findElement {using\u003daccessibility id, value\u003dApp}]\nCapabilities {appium:app: C:\\Users\\kr.pandey\\Download..., appium:appPackage: io.appium.android.apis, appium:databaseEnabled: false, appium:desired: {app: C:\\Users\\kr.pandey\\Download..., deviceName: Pixel 6 API 30, platformName: android, udid: emulator-5554}, appium:deviceApiLevel: 30, appium:deviceManufacturer: unknown, appium:deviceModel: Android SDK built for x86, appium:deviceName: emulator-5554, appium:deviceScreenDensity: 420, appium:deviceScreenSize: 1080x2400, appium:deviceUDID: emulator-5554, appium:javascriptEnabled: true, appium:locationContextEnabled: false, appium:networkConnectionEnabled: true, appium:pixelRatio: 2.625, appium:platformVersion: 11, appium:statBarHeight: 136, appium:takesScreenshot: true, appium:udid: emulator-5554, appium:viewportRect: {height: 2002, left: 0, top: 136, width: 1080}, appium:warnings: {}, appium:webStorageEnabled: false, platformName: ANDROID}\nSession ID: a2840bad-ebd8-4ce5-8a16-353921c4160b\nFor documentation on this error, please visit: https://selenium.dev/exceptions/#no_such_element\nBuild info: version: \u00274.5.0\u0027, revision: \u0027fe167b119a\u0027\nSystem info: os.name: \u0027Windows 10\u0027, os.arch: \u0027amd64\u0027, os.version: \u002710.0\u0027, java.version: \u00271.8.0_352\u0027\nDriver info: driver.version: unknown","testFailureSummary":"ERROR;org.openqa.selenium.NoSuchElementException;An element could not be located on the page using the given search parameters.\nFor documentation on this error, please visit: https://selenium.dev/exceptions/#no_such_element\nBuild info: version: \u00274.5.0\u0027, revision: \u0027fe167b119a\u0027\nSystem info: os.name: \u0027Windows 10\u0027, os.arch: \u0027amd64\u0027, os.version: \u002710.0\u0027, java.version: \u00271.8.0_352\u0027\nDriver info: io.appium.java_client.android.AndroidDriver\nCommand: [a2840bad-ebd8-4ce5-8a16-353921c4160b, findElement {using\u003daccessibility id, value\u003dApp}]\nCapabilities {appium:app: C:\\Users\\kr.pandey\\Download..., appium:appPackage: io.appium.android.apis, appium:databaseEnabled: false, appium:desired: {app: C:\\Users\\kr.pandey\\Download..., deviceName: Pixel 6 API 30, platformName: android, udid: emulator-5554}, appium:deviceApiLevel: 30, appium:deviceManufacturer: unknown, appium:deviceModel: Android SDK built for x86, appium:deviceName: emulator-5554, appium:deviceScreenDensity: 420, appium:deviceScreenSize: 1080x2400, appium:deviceUDID: emulator-5554, appium:javascriptEnabled: true, appium:locationContextEnabled: false, appium:networkConnectionEnabled: true, appium:pixelRatio: 2.625, appium:platformVersion: 11, appium:statBarHeight: 136, appium:takesScreenshot: true, appium:udid: emulator-5554, appium:viewportRect: {height: 2002, left: 0, top: 136, width: 1080}, appium:warnings: {}, appium:webStorageEnabled: false, platformName: ANDROID}\nSession ID: a2840bad-ebd8-4ce5-8a16-353921c4160b\nFor documentation on this error, please visit: https://selenium.dev/exceptions/#no_such_element\nBuild info: version: \u00274.5.0\u0027, revision: \u0027fe167b119a\u0027\nSystem info: os.name: \u0027Windows 10\u0027, os.arch: \u0027amd64\u0027, os.version: \u002710.0\u0027, java.version: \u00271.8.0_352\u0027\nDriver info: driver.version: unknown;AppiumCommandExecutor.java","projectKey":"","annotatedResult":"ERROR","isManualTestingUpToDate":false,"manual":false,"testSource":"Cucumber","result":"ERROR"}